smplkit/__init__.py
smplkit/__version__.py
smplkit/constants.py
smplkit/layers.py
smplkit/lbs.py
smplkit/misc.py
smplkit/params.py
smplkit/utils.py
smplkit-0.0.3.dist-info/LICENSE
smplkit-0.0.3.dist-info/METADATA
smplkit-0.0.3.dist-info/WHEEL
smplkit-0.0.3.dist-info/top_level.txt
smplkit-0.0.3.dist-info/RECORD
