Metadata-Version: 2.1
Name: smplkit
Version: 0.0.3
Summary: SMPL-KIT: Use SMPL models more easily.
Home-page: https://github.com/Silverster98/smpl-kit
Author: Zan Wang
Author-email: zanwang98@gmail.com
License: MIT
Classifier: License :: OSI Approved :: MIT License
Classifier: Programming Language :: Python
Classifier: Programming Language :: Python :: 3
Classifier: Programming Language :: Python :: 3.6
Classifier: Programming Language :: Python :: 3.7
Classifier: Programming Language :: Python :: 3.8
Classifier: Programming Language :: Python :: 3.9
Classifier: Programming Language :: Python :: 3.10
Classifier: Programming Language :: Python :: 3.11
Classifier: Programming Language :: Python :: 3.12
Classifier: Programming Language :: Python :: Implementation :: CPython
Classifier: Programming Language :: Python :: Implementation :: PyPy
Requires-Python: >=3.6.0
License-File: LICENSE
Requires-Dist: numpy (>=1.19.0)
Requires-Dist: einops (>=0.3.0)
Requires-Dist: torch (>=1.6.0)
Requires-Dist: pytorch3d (>=0.6.0)
Requires-Dist: easydict (>=1.9)
